arranger-1.1.2.data/scripts/arrange
engine/__init__.py
engine/DIR/DIR.py
engine/DIR/__init__.py
engine/DIR/dir_tests.py
engine/Extensions/Extensions.py
engine/Extensions/__init__.py
engine/Extensions/extension_tests.py
engine/File/File.py
engine/File/__init__.py
arranger-1.1.2.dist-info/LICENSE.txt
arranger-1.1.2.dist-info/METADATA
arranger-1.1.2.dist-info/WHEEL
arranger-1.1.2.dist-info/top_level.txt
arranger-1.1.2.dist-info/RECORD
